json_multi_merge-0.3.1.dist-info/METADATA
json_multi_merge-0.3.1.dist-info/WHEEL
json_multi_merge-0.3.1.dist-info/licenses/LICENSE.txt
json_multi_merge.libs/libgcc_s-1e52349c.so.1
json_multi_merge/__init__.py
json_multi_merge/json_multi_merge.abi3.so
json_multi_merge-0.3.1.dist-info/RECORD
