Metadata-Version: 2.4
Name: json-multi-merge
Version: 0.3.1
Classifier: Programming Language :: Rust
Classifier: Programming Language :: Python :: 3
Classifier: License :: OSI Approved :: MIT License
Classifier: Operating System :: OS Independent
License-File: LICENSE.txt
Summary: Rust-powered JSON merging with custom modifiers
Author: Nic Wolff <nwolff@hearst.com>
Author-email: Nic Wolff <nwolff@hearst.com>
License: MIT
Requires-Python: >=3.8
Project-URL: Source Code, https://github.com/Media-Platforms/json-multi-merge
